hexes/__init__.py
hexes/aiotextpad.py
hexes/behaviors.py
hexes/hexes.py
hexes/utils.py
hexes-0.4.0.data/scripts/hexes_example
hexes-0.4.0.dist-info/DESCRIPTION.rst
hexes-0.4.0.dist-info/METADATA
hexes-0.4.0.dist-info/metadata.json
hexes-0.4.0.dist-info/RECORD
hexes-0.4.0.dist-info/top_level.txt
hexes-0.4.0.dist-info/WHEEL
