Metadata-Version: 2.0
Name: hexes
Version: 0.4.0
Summary: Curses for humans.
Home-page: https://github.com/wlonk/hexes
Author: Kit La Touche
Author-email: kit@transneptune.net
License: BSD
Keywords: hexes
Platform: UNKNOWN
Classifier: Development Status :: 3 - Alpha
Classifier: Intended Audience :: Developers
Classifier: License :: OSI Approved :: BSD License
Classifier: Natural Language :: English
Classifier: Programming Language :: Python :: 3
Classifier: Programming Language :: Python :: 3.4
Classifier: Environment :: Console
Classifier: Environment :: Console :: Curses
Requires-Dist: wheel (==0.24.0)
